{"acteur": {"@xmlns": "http://schemas.assemblee-nationale.fr/referentiel", "uid": {"@xmlns:xsi": "http://www.w3.org/2001/XMLSchema-instance", "@xsi:type": "IdActeur_type", "#text": "PA609726"}, "etatCivil": {"ident": {"civ": "M.", "prenom": "Julien", "nom": "Aubert", "alpha": "Aubert", "trigramme": "JAU"}, "infoNaissance": {"dateNais": "1978-06-11", "villeNais": "Marseille", "depNais": "Bouches-du-Rh\u00f4ne", "paysNais": "France"}, "dateDeces": {"@xmlns:xsi": "http://www.w3.org/2001/XMLSchema-instance", "@xsi:nil": "true"}}, "profession": {"libelleCourant": "Magistrat \u00e0 la Cour des Comptes", "socProcINSEE": {"catSocPro": "Cadres de la fonction publique, professions intellectuelles et  artistiques", "famSocPro": "Cadres et professions intellectuelles sup\u00e9rieures"}}, "uri_hatvp": "https://www.hatvp.fr/pages_nominatives/aubert-julien", "adresses": {"adresse": [{"@xmlns:xsi": "http://www.w3.org/2001/XMLSchema-instance", "@xsi:type": "AdresseMail_Type", "uid": "AD648497", "type": "15", "typeLibelle": "M\u00e8l", "poids": null, "adresseDeRattachement": null, "valElec": "julien.aubert@assemblee-nationale.fr"}, {"@xmlns:xsi": "http://www.w3.org/2001/XMLSchema-instance", "@xsi:type": "AdressePostale_Type", "uid": "AD650499", "type": "0", "typeLibelle": "Adresse officielle", "poids": "1", "adresseDeRattachement": null, "intitule": "Assembl\u00e9e nationale", "numeroRue": "126", "nomRue": "Rue de l'Universit\u00e9", "complementAdresse": null, "codePostal": "75355", "ville": "Paris 07 SP"}, {"@xmlns:xsi": "http://www.w3.org/2001/XMLSchema-instance", "@xsi:type": "AdressePostale_Type", "uid": "AD650501", "type": "2", "typeLibelle": "Adresse publi\u00e9e de circonscription", "poids": "22", "adresseDeRattachement": null, "intitule": "Permanence parlementaire", "numeroRue": "202", "nomRue": "Avenue du Mont Ventoux", "complementAdresse": "BP 70045", "codePostal": "84200", "ville": "Carpentras"}, {"@xmlns:xsi": "http://www.w3.org/2001/XMLSchema-instance", "@xsi:type": "AdresseTelephonique_Type", "uid": "AD650502", "type": "11", "typeLibelle": "T\u00e9l\u00e9phone", "poids": "22", "adresseDeRattachement": "AD650501", "valElec": "04 90 67 94 12"}, {"@xmlns:xsi": "http://www.w3.org/2001/XMLSchema-instance", "@xsi:type": "AdresseMail_Type", "uid": "AD701400", "type": "15", "typeLibelle": "M\u00e8l", "poids": null, "adresseDeRattachement": null, "valElec": "contact@julienaubert.fr"}, {"@xmlns:xsi": "http://www.w3.org/2001/XMLSchema-instance", "@xsi:type": "AdresseSiteWeb_Type", "uid": "AD725696", "type": "22", "typeLibelle": "Site internet", "poids": null, "adresseDeRattachement": null, "valElec": "www.julienaubert.fr"}, {"@xmlns:xsi": "http://www.w3.org/2001/XMLSchema-instance", "@xsi:type": "AdresseSiteWeb_Type", "uid": "AD784811", "type": "25", "typeLibelle": "Facebook", "poids": null, "adresseDeRattachement": null, "valElec": "JulienAubert.fr"}, {"@xmlns:xsi": "http://www.w3.org/2001/XMLSchema-instance", "@xsi:type": "AdresseSiteWeb_Type", "uid": "AD784813", "type": "24", "typeLibelle": "Twitter", "poids": null, "adresseDeRattachement": null, "valElec": "@JulienAubert84"}, {"@xmlns:xsi": "http://www.w3.org/2001/XMLSchema-instance", "@xsi:type": "AdresseSiteWeb_Type", "uid": "AD785104", "type": "29", "typeLibelle": "Instagram", "poids": null, "adresseDeRattachement": null, "valElec": "julienaubert84"}]}, "mandats": {"mandat": [{"@xmlns:xsi": "http://www.w3.org/2001/XMLSchema-instance", "@xsi:type": "MandatAvecSuppleant_Type", "uid": "PM732605", "acteurRef": "PA609726", "legislature": "15", "typeOrgane": "OFFPAR", "dateDebut": "2017-07-12", "datePublication": "2017-07-12", "dateFin": null, "preseance": "24", "nominPrincipale": "1", "infosQualite": {"codeQualite": "Membre", "libQualite": "Membre", "libQualiteSex": "Membre"}, "organes": {"organeRef": "PO273589"}, "suppleants": null}, {"@xmlns:xsi": "http://www.w3.org/2001/XMLSchema-instance", "@xsi:type": "MandatMission_Type", "uid": "PM772410", "acteurRef": "PA609726", "legislature": "15", "typeOrgane": "MISINFOPRE", "dateDebut": "2020-06-11", "datePublication": "2020-06-11", "dateFin": "2021-01-27", "preseance": "20", "nominPrincipale": "1", "infosQualite": {"codeQualite": "Membre", "libQualite": "Membre", "libQualiteSex": "Membre"}, "organes": {"organeRef": "PO771231"}, "libelle": null, "missionSuivanteRef": null, "missionPrecedenteRef": null}, {"@xmlns:xsi": "http://www.w3.org/2001/XMLSchema-instance", "@xsi:type": "MandatMission_Type", "uid": "PM748301", "acteurRef": "PA609726", "legislature": "15", "typeOrgane": "MISINFOCOM", "dateDebut": "2018-02-01", "datePublication": "2018-02-01", "dateFin": "2018-12-12", "preseance": "20", "nominPrincipale": "1", "infosQualite": {"codeQualite": "Membre", "libQualite": "Membre", "libQualiteSex": "Membre"}, "organes": {"organeRef": "PO748278"}, "libelle": null, "missionSuivanteRef": null, "missionPrecedenteRef": null}, {"@xmlns:xsi": "http://www.w3.org/2001/XMLSchema-instance", "@xsi:type": "MandatSimple_Type", "uid": "PM745619", "acteurRef": "PA609726", "legislature": null, "typeOrgane": "PARPOL", "dateDebut": "2017-12-01", "datePublication": null, "dateFin": null, "preseance": "5", "nominPrincipale": "1", "infosQualite": {"codeQualite": "Membre", "libQualite": "Membre", "libQualiteSex": "Membre"}, "organes": {"organeRef": "PO710396"}}, {"@xmlns:xsi": "http://www.w3.org/2001/XMLSchema-instance", "@xsi:type": "MandatSimple_Type", "uid": "PM710408", "acteurRef": "PA609726", "legislature": null, "typeOrgane": "PARPOL", "dateDebut": "2015-12-01", "datePublication": null, "dateFin": "2017-06-20", "preseance": "5", "nominPrincipale": "1", "infosQualite": {"codeQualite": "Membre", "libQualite": "Membre", "libQualiteSex": "Membre"}, "organes": {"organeRef": "PO710396"}}, {"@xmlns:xsi": "http://www.w3.org/2001/XMLSchema-instance", "@xsi:type": "MandatSimple_Type", "uid": "PM691672", "acteurRef": "PA609726", "legislature": "14", "typeOrgane": "GEVI", "dateDebut": "2013-02-20", "datePublication": null, "dateFin": "2017-06-20", "preseance": "20", "nominPrincipale": "1", "infosQualite": {"codeQualite": "Membre", "libQualite": "Membre", "libQualiteSex": "Membre"}, "organes": {"organeRef": "PO675743"}}, {"@xmlns:xsi": "http://www.w3.org/2001/XMLSchema-instance", "@xsi:type": "MandatSimple_Type", "uid": "PM781221", "acteurRef": "PA609726", "legislature": "15", "typeOrgane": "CNPS", "dateDebut": "2021-02-14", "datePublication": "2021-02-14", "dateFin": "2021-08-22", "preseance": "20", "nominPrincipale": "1", "infosQualite": {"codeQualite": "Membre", "libQualite": "Membre", "libQualiteSex": "Membre"}, "organes": {"organeRef": "PO780850"}}, {"@xmlns:xsi": "http://www.w3.org/2001/XMLSchema-instance", "@xsi:type": "MandatSimple_Type", "uid": "PM744803", "acteurRef": "PA609726", "legislature": "15", "typeOrgane": "CNPS", "dateDebut": "2017-12-06", "datePublication": "2017-12-06", "dateFin": "2018-07-31", "preseance": "20", "nominPrincipale": "1", "infosQualite": {"codeQualite": "Membre", "libQualite": "Membre", "libQualiteSex": "Membre"}, "organes": {"organeRef": "PO744107"}}, {"@xmlns:xsi": "http://www.w3.org/2001/XMLSchema-instance", "@xsi:type": "MandatSimple_Type", "uid": "PM762980", "acteurRef": "PA609726", "legislature": "15", "typeOrgane": "CNPE", "dateDebut": "2019-03-05", "datePublication": "2019-03-06", "dateFin": "2019-07-25", "preseance": "20", "nominPrincipale": "1", "infosQualite": {"codeQualite": "Membre", "libQualite": "Membre", "libQualiteSex": "Membre"}, "organes": {"organeRef": "PO762821"}}, {"@xmlns:xsi": "http://www.w3.org/2001/XMLSchema-instance", "@xsi:type": "MandatSimple_Type", "uid": "PM749013", "acteurRef": "PA609726", "legislature": "15", "typeOrgane": "CNPE", "dateDebut": "2018-02-08", "datePublication": "2018-02-08", "dateFin": "2018-06-28", "preseance": "20", "nominPrincipale": "0", "infosQualite": {"codeQualite": "Membre", "libQualite": "Membre", "libQualiteSex": "Membre"}, "organes": {"organeRef": "PO748336"}}, {"@xmlns:xsi": "http://www.w3.org/2001/XMLSchema-instance", "@xsi:type": "MandatSimple_Type", "uid": "PM755447", "acteurRef": "PA609726", "legislature": "15", "typeOrgane": "CNPE", "dateDebut": "2018-04-14", "datePublication": "2018-04-14", "dateFin": "2018-09-28", "preseance": "20", "nominPrincipale": "1", "infosQualite": {"codeQualite": "Membre", "libQualite": "Membre", "libQualiteSex": "Membre"}, "organes": {"organeRef": "PO754360"}}, {"@xmlns:xsi": "http://www.w3.org/2001/XMLSchema-instance", "@xsi:type": "MandatSimple_Type", "uid": "PM743003", "acteurRef": "PA609726", "legislature": "15", "typeOrgane": "ORGEXTPARL", "dateDebut": "2017-11-10", "datePublication": "2017-11-11", "dateFin": null, "preseance": "20", "nominPrincipale": "1", "infosQualite": {"codeQualite": "Titulaire", "libQualite": "Membre titulaire", "libQualiteSex": "Membre titulaire"}, "organes": {"organeRef": "PO60170"}}, {"@xmlns:xsi": "http://www.w3.org/2001/XMLSchema-instance", "@xsi:type": "MandatSimple_Type", "uid": "PM748012", "acteurRef": "PA609726", "legislature": "15", "typeOrgane": "ORGEXTPARL", "dateDebut": "2018-01-10", "datePublication": "2018-01-11", "dateFin": null, "preseance": "20", "nominPrincipale": "1", "infosQualite": {"codeQualite": "Titulaire", "libQualite": "Membre titulaire", "libQualiteSex": "Membre titulaire"}, "organes": {"organeRef": "PO717436"}}, {"@xmlns:xsi": "http://www.w3.org/2001/XMLSchema-instance", "@xsi:type": "MandatSimple_Type", "uid": "PM743712", "acteurRef": "PA609726", "legislature": "15", "typeOrgane": "ORGEXTPARL", "dateDebut": "2017-11-21", "datePublication": "2017-11-22", "dateFin": null, "preseance": "20", "nominPrincipale": "1", "infosQualite": {"codeQualite": "Titulaire", "libQualite": "Membre titulaire", "libQualiteSex": "Membre titulaire"}, "organes": {"organeRef": "PO201361"}}, {"@xmlns:xsi": "http://www.w3.org/2001/XMLSchema-instance", "@xsi:type": "MandatMission_Type", "uid": "PM749085", "acteurRef": "PA609726", "legislature": "15", "typeOrgane": "MISINFOCOM", "dateDebut": "2018-02-08", "datePublication": "2018-02-08", "dateFin": "2018-12-12", "preseance": "1", "nominPrincipale": "1", "infosQualite": {"codeQualite": "Pr\u00e9sident", "libQualite": "Pr\u00e9sident", "libQualiteSex": "Pr\u00e9sident"}, "organes": {"organeRef": "PO748278"}, "libelle": null, "missionSuivanteRef": null, "missionPrecedenteRef": null}, {"@xmlns:xsi": "http://www.w3.org/2001/XMLSchema-instance", "@xsi:type": "MandatSimple_Type", "uid": "PM731305", "acteurRef": "PA609726", "legislature": "15", "typeOrgane": "GP", "dateDebut": "2017-06-27", "datePublication": "2017-06-28", "dateFin": null, "preseance": "20", "nominPrincipale": "1", "infosQualite": {"codeQualite": "Membre", "libQualite": "Membre du", "libQualiteSex": "Membre du"}, "organes": {"organeRef": "PO730934"}}, {"@xmlns:xsi": "http://www.w3.org/2001/XMLSchema-instance", "@xsi:type": "MandatSimple_Type", "uid": "PM708104", "acteurRef": "PA609726", "legislature": "14", "typeOrgane": "GP", "dateDebut": "2015-06-02", "datePublication": "2015-06-02", "dateFin": "2017-06-20", "preseance": "20", "nominPrincipale": "1", "infosQualite": {"codeQualite": "Membre", "libQualite": "Membre du", "libQualiteSex": "Membre du"}, "organes": {"organeRef": "PO707869"}}, {"@xmlns:xsi": "http://www.w3.org/2001/XMLSchema-instance", "@xsi:type": "MandatSimple_Type", "uid": "PM781366", "acteurRef": "PA609726", "legislature": "15", "typeOrgane": "CNPS", "dateDebut": "2021-02-16", "datePublication": "2021-02-17", "dateFin": "2021-08-22", "preseance": "14", "nominPrincipale": "1", "infosQualite": {"codeQualite": "Secr\u00e9taire", "libQualite": "Secr\u00e9taire", "libQualiteSex": "Secr\u00e9taire"}, "organes": {"organeRef": "PO780850"}}, {"@xmlns:xsi": "http://www.w3.org/2001/XMLSchema-instance", "@xsi:type": "MandatSimple_Type", "uid": "PM757185", "acteurRef": "PA609726", "legislature": "15", "typeOrgane": "COMPER", "dateDebut": "2018-06-23", "datePublication": "2018-06-23", "dateFin": "2019-06-17", "preseance": "32", "nominPrincipale": "1", "infosQualite": {"codeQualite": "Membre", "libQualite": "Membre", "libQualiteSex": "Membre"}, "organes": {"organeRef": "PO59048"}}, {"@xmlns:xsi": "http://www.w3.org/2001/XMLSchema-instance", "@xsi:type": "MandatSimple_Type", "uid": "PM786157", "acteurRef": "PA609726", "legislature": "15", "typeOrgane": "COMPER", "dateDebut": "2021-10-07", "datePublication": "2021-10-07", "dateFin": "2021-10-07", "preseance": "32", "nominPrincipale": "1", "infosQualite": {"codeQualite": "Membre", "libQualite": "Membre", "libQualiteSex": "Membre"}, "organes": {"organeRef": "PO419865"}}, {"@xmlns:xsi": "http://www.w3.org/2001/XMLSchema-instance", "@xsi:type": "MandatSimple_Type", "uid": "PM731691", "acteurRef": "PA609726", "legislature": "15", "typeOrgane": "COMPER", "dateDebut": "2017-06-29", "datePublication": "2017-06-29", "dateFin": "2018-06-11", "preseance": "32", "nominPrincipale": "1", "infosQualite": {"codeQualite": "Membre", "libQualite": "Membre", "libQualiteSex": "Membre"}, "organes": {"organeRef": "PO59048"}}, {"@xmlns:xsi": "http://www.w3.org/2001/XMLSchema-instance", "@xsi:type": "MandatSimple_Type", "uid": "PM756847", "acteurRef": "PA609726", "legislature": "15", "typeOrgane": "COMPER", "dateDebut": "2018-06-12", "datePublication": "2018-06-12", "dateFin": "2018-06-22", "preseance": "32", "nominPrincipale": "1", "infosQualite": {"codeQualite": "Membre", "libQualite": "Membre", "libQualiteSex": "Membre"}, "organes": {"organeRef": "PO419610"}}, {"@xmlns:xsi": "http://www.w3.org/2001/XMLSchema-instance", "@xsi:type": "MandatSimple_Type", "uid": "PM765798", "acteurRef": "PA609726", "legislature": "15", "typeOrgane": "COMPER", "dateDebut": "2019-06-18", "datePublication": "2019-06-18", "dateFin": "2019-06-20", "preseance": "32", "nominPrincipale": "1", "infosQualite": {"codeQualite": "Membre", "libQualite": "Membre", "libQualiteSex": "Membre"}, "organes": {"organeRef": "PO419610"}}, {"@xmlns:xsi": "http://www.w3.org/2001/XMLSchema-instance", "@xsi:type": "MandatSimple_Type", "uid": "PM710647", "acteurRef": "PA609726", "legislature": "14", "typeOrgane": "COMPER", "dateDebut": "2015-12-04", "datePublication": "2015-12-04", "dateFin": "2017-06-20", "preseance": "32", "nominPrincipale": "1", "infosQualite": {"codeQualite": "Membre", "libQualite": "Membre", "libQualiteSex": "Membre"}, "organes": {"organeRef": "PO419865"}}, {"@xmlns:xsi": "http://www.w3.org/2001/XMLSchema-instance", "@xsi:type": "MandatSimple_Type", "uid": "PM778679", "acteurRef": "PA609726", "legislature": "15", "typeOrgane": "COMPER", "dateDebut": "2020-11-18", "datePublication": "2020-11-18", "dateFin": "2020-12-04", "preseance": "32", "nominPrincipale": "1", "infosQualite": {"codeQualite": "Membre", "libQualite": "Membre", "libQualiteSex": "Membre"}, "organes": {"organeRef": "PO419865"}}, {"@xmlns:xsi": "http://www.w3.org/2001/XMLSchema-instance", "@xsi:type": "MandatSimple_Type", "uid": "PM786187", "acteurRef": "PA609726", "legislature": "15", "typeOrgane": "COMPER", "dateDebut": "2021-10-08", "datePublication": "2021-10-08", "dateFin": null, "preseance": "32", "nominPrincipale": "1", "infosQualite": {"codeQualite": "Membre", "libQualite": "Membre", "libQualiteSex": "Membre"}, "organes": {"organeRef": "PO59048"}}, {"@xmlns:xsi": "http://www.w3.org/2001/XMLSchema-instance", "@xsi:type": "MandatSimple_Type", "uid": "PM778902", "acteurRef": "PA609726", "legislature": "15", "typeOrgane": "COMPER", "dateDebut": "2020-12-05", "datePublication": "2020-12-05", "dateFin": "2021-10-06", "preseance": "32", "nominPrincipale": "1", "infosQualite": {"codeQualite": "Membre", "libQualite": "Membre", "libQualiteSex": "Membre"}, "organes": {"organeRef": "PO59048"}}, {"@xmlns:xsi": "http://www.w3.org/2001/XMLSchema-instance", "@xsi:type": "MandatSimple_Type", "uid": "PM765885", "acteurRef": "PA609726", "legislature": "15", "typeOrgane": "COMPER", "dateDebut": "2019-06-21", "datePublication": "2019-06-21", "dateFin": "2020-11-17", "preseance": "32", "nominPrincipale": "1", "infosQualite": {"codeQualite": "Membre", "libQualite": "Membre", "libQualiteSex": "Membre"}, "organes": {"organeRef": "PO59048"}}, {"@xmlns:xsi": "http://www.w3.org/2001/XMLSchema-instance", "@xsi:type": "MandatSimple_Type", "uid": "PM749117", "acteurRef": "PA609726", "legislature": "15", "typeOrgane": "CNPE", "dateDebut": "2018-02-08", "datePublication": "2018-02-09", "dateFin": "2018-06-28", "preseance": "8", "nominPrincipale": "1", "infosQualite": {"codeQualite": "Vice-Pr\u00e9sident", "libQualite": "Vice-Pr\u00e9sident", "libQualiteSex": "Vice-Pr\u00e9sident"}, "organes": {"organeRef": "PO748336"}}, {"@xmlns:xsi": "http://www.w3.org/2001/XMLSchema-instance", "@xsi:type": "MandatSimple_Type", "uid": "PM763088", "acteurRef": "PA609726", "legislature": "15", "typeOrgane": "CNPE", "dateDebut": "2019-03-07", "datePublication": "2019-03-08", "dateFin": "2019-07-25", "preseance": "1", "nominPrincipale": "1", "infosQualite": {"codeQualite": "Pr\u00e9sident", "libQualite": "Pr\u00e9sident", "libQualiteSex": "Pr\u00e9sident"}, "organes": {"organeRef": "PO762821"}}, {"@xmlns:xsi": "http://www.w3.org/2001/XMLSchema-instance", "@xsi:type": "MandatSimple_Type", "uid": "PM696839", "acteurRef": "PA609726", "legislature": "14", "typeOrgane": "ORGEXTPARL", "dateDebut": "2013-09-05", "datePublication": "2013-09-06", "dateFin": "2017-06-20", "preseance": "20", "nominPrincipale": "1", "infosQualite": {"codeQualite": "Titulaire", "libQualite": "Membre titulaire", "libQualiteSex": "Membre titulaire"}, "organes": {"organeRef": "PO696836"}}, {"@xmlns:xsi": "http://www.w3.org/2001/XMLSchema-instance", "@xsi:type": "MandatSimple_Type", "uid": "PM743541", "acteurRef": "PA609726", "legislature": "15", "typeOrgane": "CMP", "dateDebut": "2017-11-16", "datePublication": "2017-11-16", "dateFin": "2017-12-19", "preseance": "20", "nominPrincipale": "1", "infosQualite": {"codeQualite": "Titulaire", "libQualite": "Membre titulaire", "libQualiteSex": "Membre titulaire"}, "organes": {"organeRef": "PO742823"}}, {"@xmlns:xsi": "http://www.w3.org/2001/XMLSchema-instance", "@xsi:type": "MandatSimple_Type", "uid": "PM779073", "acteurRef": "PA609726", "legislature": "15", "typeOrgane": "CMP", "dateDebut": "2020-12-09", "datePublication": "2020-12-11", "dateFin": "2020-12-16", "preseance": "20", "nominPrincipale": "1", "infosQualite": {"codeQualite": "Titulaire", "libQualite": "Membre titulaire", "libQualiteSex": "Membre titulaire"}, "organes": {"organeRef": "PO779061"}}, {"@xmlns:xsi": "http://www.w3.org/2001/XMLSchema-instance", "@xsi:type": "MandatSimple_Type", "uid": "PM789256", "acteurRef": "PA609726", "legislature": "15", "typeOrgane": "CMP", "dateDebut": "2022-01-26", "datePublication": "2022-01-27", "dateFin": "2022-02-15", "preseance": "20", "nominPrincipale": "1", "infosQualite": {"codeQualite": "Titulaire", "libQualite": "Membre titulaire", "libQualiteSex": "Membre titulaire"}, "organes": {"organeRef": "PO789233"}}, {"@xmlns:xsi": "http://www.w3.org/2001/XMLSchema-instance", "@xsi:type": "MandatSimple_Type", "uid": "PM784449", "acteurRef": "PA609726", "legislature": "15", "typeOrgane": "CMP", "dateDebut": "2021-07-07", "datePublication": "2021-07-08", "dateFin": "2021-07-20", "preseance": "20", "nominPrincipale": "1", "infosQualite": {"codeQualite": "Titulaire", "libQualite": "Membre titulaire", "libQualiteSex": "Membre titulaire"}, "organes": {"organeRef": "PO784067"}}, {"@xmlns:xsi": "http://www.w3.org/2001/XMLSchema-instance", "@xsi:type": "MandatSimple_Type", "uid": "PM766566", "acteurRef": "PA609726", "legislature": "15", "typeOrgane": "CMP", "dateDebut": "2019-07-18", "datePublication": "2019-07-19", "dateFin": "2019-09-26", "preseance": "20", "nominPrincipale": "1", "infosQualite": {"codeQualite": "Titulaire", "libQualite": "Membre titulaire", "libQualiteSex": "Membre titulaire"}, "organes": {"organeRef": "PO766528"}}, {"@xmlns:xsi": "http://www.w3.org/2001/XMLSchema-instance", "@xsi:type": "MandatSimple_Type", "uid": "PM724754", "acteurRef": "PA609726", "legislature": "15", "typeOrgane": "GP", "dateDebut": "2017-06-21", "datePublication": null, "dateFin": "2017-06-26", "preseance": "28", "nominPrincipale": "1", "infosQualite": {"codeQualite": "D\u00e9put\u00e9 non-inscrit", "libQualite": "D\u00e9put\u00e9 non-inscrit", "libQualiteSex": "D\u00e9put\u00e9 non-inscrit"}, "organes": {"organeRef": "PO723569"}}, {"@xmlns:xsi": "http://www.w3.org/2001/XMLSchema-instance", "@xsi:type": "MandatSimple_Type", "uid": "PM688622", "acteurRef": "PA609726", "legislature": "14", "typeOrgane": "GE", "dateDebut": "2013-01-24", "datePublication": null, "dateFin": "2017-06-20", "preseance": "20", "nominPrincipale": "1", "infosQualite": {"codeQualite": "Membre", "libQualite": "Membre", "libQualiteSex": "Membre"}, "organes": {"organeRef": "PO686232"}}, {"@xmlns:xsi": "http://www.w3.org/2001/XMLSchema-instance", "@xsi:type": "MandatSimple_Type", "uid": "PM695138", "acteurRef": "PA609726", "legislature": "14", "typeOrgane": "GE", "dateDebut": "2012-12-18", "datePublication": null, "dateFin": "2017-06-20", "preseance": "20", "nominPrincipale": "1", "infosQualite": {"codeQualite": "Membre", "libQualite": "Membre", "libQualiteSex": "Membre"}, "organes": {"organeRef": "PO686266"}}, {"@xmlns:xsi": "http://www.w3.org/2001/XMLSchema-instance", "@xsi:type": "MandatSimple_Type", "uid": "PM694410", "acteurRef": "PA609726", "legislature": "14", "typeOrgane": "GE", "dateDebut": "2013-01-18", "datePublication": null, "dateFin": "2017-06-20", "preseance": "20", "nominPrincipale": "1", "infosQualite": {"codeQualite": "Membre", "libQualite": "Membre", "libQualiteSex": "Membre"}, "organes": {"organeRef": "PO687403"}}, {"@xmlns:xsi": "http://www.w3.org/2001/XMLSchema-instance", "@xsi:type": "MandatSimple_Type", "uid": "PM688911", "acteurRef": "PA609726", "legislature": "14", "typeOrgane": "GE", "dateDebut": "2013-01-25", "datePublication": null, "dateFin": "2017-06-20", "preseance": "20", "nominPrincipale": "1", "infosQualite": {"codeQualite": "Membre", "libQualite": "Membre", "libQualiteSex": "Membre"}, "organes": {"organeRef": "PO686577"}}, {"@xmlns:xsi": "http://www.w3.org/2001/XMLSchema-instance", "@xsi:type": "MandatSimple_Type", "uid": "PM687104", "acteurRef": "PA609726", "legislature": "14", "typeOrgane": "GE", "dateDebut": "2012-12-14", "datePublication": null, "dateFin": "2017-06-20", "preseance": "20", "nominPrincipale": "0", "infosQualite": {"codeQualite": "Membre", "libQualite": "Membre", "libQualiteSex": "Membre"}, "organes": {"organeRef": "PO687098"}}, {"@xmlns:xsi": "http://www.w3.org/2001/XMLSchema-instance", "@xsi:type": "MandatSimple_Type", "uid": "PM752276", "acteurRef": "PA609726", "legislature": "15", "typeOrgane": "GE", "dateDebut": "2018-03-05", "datePublication": null, "dateFin": null, "preseance": "20", "nominPrincipale": "1", "infosQualite": {"codeQualite": "Membre", "libQualite": "Membre", "libQualiteSex": "Membre"}, "organes": {"organeRef": "PO746837"}}, {"@xmlns:xsi": "http://www.w3.org/2001/XMLSchema-instance", "@xsi:type": "MandatSimple_Type", "uid": "PM690516", "acteurRef": "PA609726", "legislature": "14", "typeOrgane": "GE", "dateDebut": "2013-01-29", "datePublication": null, "dateFin": "2017-06-20", "preseance": "20", "nominPrincipale": "1", "infosQualite": {"codeQualite": "Membre", "libQualite": "Membre", "libQualiteSex": "Membre"}, "organes": {"organeRef": "PO686861"}}, {"@xmlns:xsi": "http://www.w3.org/2001/XMLSchema-instance", "@xsi:type": "MandatSimple_Type", "uid": "PM748886", "acteurRef": "PA609726", "legislature": "15", "typeOrgane": "GE", "dateDebut": "2018-02-01", "datePublication": null, "dateFin": null, "preseance": "20", "nominPrincipale": "0", "infosQualite": {"codeQualite": "Membre", "libQualite": "Membre", "libQualiteSex": "Membre"}, "organes": {"organeRef": "PO746899"}}, {"@xmlns:xsi": "http://www.w3.org/2001/XMLSchema-instance", "@xsi:type": "MandatSimple_Type", "uid": "PM689325", "acteurRef": "PA609726", "legislature": "14", "typeOrgane": "GE", "dateDebut": "2013-01-29", "datePublication": null, "dateFin": "2017-06-20", "preseance": "20", "nominPrincipale": "1", "infosQualite": {"codeQualite": "Membre", "libQualite": "Membre", "libQualiteSex": "Membre"}, "organes": {"organeRef": "PO686188"}}, {"@xmlns:xsi": "http://www.w3.org/2001/XMLSchema-instance", "@xsi:type": "MandatSimple_Type", "uid": "PM698891", "acteurRef": "PA609726", "legislature": "14", "typeOrgane": "GE", "dateDebut": "2013-07-31", "datePublication": null, "dateFin": "2017-06-20", "preseance": "20", "nominPrincipale": "1", "infosQualite": {"codeQualite": "Membre", "libQualite": "Membre", "libQualiteSex": "Membre"}, "organes": {"organeRef": "PO686870"}}, {"@xmlns:xsi": "http://www.w3.org/2001/XMLSchema-instance", "@xsi:type": "MandatSimple_Type", "uid": "PM753017", "acteurRef": "PA609726", "legislature": "15", "typeOrgane": "GE", "dateDebut": "2018-03-07", "datePublication": null, "dateFin": null, "preseance": "12", "nominPrincipale": "1", "infosQualite": {"codeQualite": "Secr\u00e9taire", "libQualite": "Secr\u00e9taire", "libQualiteSex": "Secr\u00e9taire"}, "organes": {"organeRef": "PO747099"}}, {"@xmlns:xsi": "http://www.w3.org/2001/XMLSchema-instance", "@xsi:type": "MandatSimple_Type", "uid": "PM692710", "acteurRef": "PA609726", "legislature": "14", "typeOrgane": "GE", "dateDebut": "2013-03-15", "datePublication": null, "dateFin": "2017-06-20", "preseance": "20", "nominPrincipale": "1", "infosQualite": {"codeQualite": "Membre", "libQualite": "Membre", "libQualiteSex": "Membre"}, "organes": {"organeRef": "PO686896"}}, {"@xmlns:xsi": "http://www.w3.org/2001/XMLSchema-instance", "@xsi:type": "MandatSimple_Type", "uid": "PM765423", "acteurRef": "PA609726", "legislature": "15", "typeOrgane": "GE", "dateDebut": "2019-05-29", "datePublication": null, "dateFin": null, "preseance": "20", "nominPrincipale": "1", "infosQualite": {"codeQualite": "Membre", "libQualite": "Membre", "libQualiteSex": "Membre"}, "organes": {"organeRef": "PO763264"}}, {"@xmlns:xsi": "http://www.w3.org/2001/XMLSchema-instance", "@xsi:type": "MandatSimple_Type", "uid": "PM689875", "acteurRef": "PA609726", "legislature": "14", "typeOrgane": "GE", "dateDebut": "2013-01-31", "datePublication": null, "dateFin": "2017-06-20", "preseance": "20", "nominPrincipale": "1", "infosQualite": {"codeQualite": "Membre", "libQualite": "Membre", "libQualiteSex": "Membre"}, "organes": {"organeRef": "PO686442"}}, {"@xmlns:xsi": "http://www.w3.org/2001/XMLSchema-instance", "@xsi:type": "MandatSimple_Type", "uid": "PM689767", "acteurRef": "PA609726", "legislature": "14", "typeOrgane": "GE", "dateDebut": "2013-01-31", "datePublication": null, "dateFin": "2017-06-20", "preseance": "20", "nominPrincipale": "1", "infosQualite": {"codeQualite": "Membre", "libQualite": "Membre", "libQualiteSex": "Membre"}, "organes": {"organeRef": "PO686362"}}, {"@xmlns:xsi": "http://www.w3.org/2001/XMLSchema-instance", "@xsi:type": "MandatSimple_Type", "uid": "PM707655", "acteurRef": "PA609726", "legislature": "14", "typeOrgane": "GE", "dateDebut": "2015-05-06", "datePublication": null, "dateFin": "2017-06-20", "preseance": "20", "nominPrincipale": "1", "infosQualite": {"codeQualite": "Membre", "libQualite": "Membre", "libQualiteSex": "Membre"}, "organes": {"organeRef": "PO705534"}}, {"@xmlns:xsi": "http://www.w3.org/2001/XMLSchema-instance", "@xsi:type": "MandatSimple_Type", "uid": "PM689557", "acteurRef": "PA609726", "legislature": "14", "typeOrgane": "GE", "dateDebut": "2013-01-20", "datePublication": null, "dateFin": "2017-06-20", "preseance": "20", "nominPrincipale": "1", "infosQualite": {"codeQualite": "Membre", "libQualite": "Membre", "libQualiteSex": "Membre"}, "organes": {"organeRef": "PO686802"}}, {"@xmlns:xsi": "http://www.w3.org/2001/XMLSchema-instance", "@xsi:type": "MandatSimple_Type", "uid": "PM750834", "acteurRef": "PA609726", "legislature": "15", "typeOrgane": "GE", "dateDebut": "2018-02-20", "datePublication": null, "dateFin": null, "preseance": "20", "nominPrincipale": "0", "infosQualite": {"codeQualite": "Membre", "libQualite": "Membre", "libQualiteSex": "Membre"}, "organes": {"organeRef": "PO747099"}}, {"@xmlns:xsi": "http://www.w3.org/2001/XMLSchema-instance", "@xsi:type": "MandatSimple_Type", "uid": "PM751028", "acteurRef": "PA609726", "legislature": "15", "typeOrgane": "GE", "dateDebut": "2018-02-19", "datePublication": null, "dateFin": null, "preseance": "20", "nominPrincipale": "1", "infosQualite": {"codeQualite": "Membre", "libQualite": "Membre", "libQualiteSex": "Membre"}, "organes": {"organeRef": "PO746880"}}, {"@xmlns:xsi": "http://www.w3.org/2001/XMLSchema-instance", "@xsi:type": "MandatSimple_Type", "uid": "PM693238", "acteurRef": "PA609726", "legislature": "14", "typeOrgane": "GE", "dateDebut": "2013-04-03", "datePublication": null, "dateFin": "2017-06-20", "preseance": "20", "nominPrincipale": "1", "infosQualite": {"codeQualite": "Membre", "libQualite": "Membre", "libQualiteSex": "Membre"}, "organes": {"organeRef": "PO689000"}}, {"@xmlns:xsi": "http://www.w3.org/2001/XMLSchema-instance", "@xsi:type": "MandatSimple_Type", "uid": "PM694939", "acteurRef": "PA609726", "legislature": "14", "typeOrgane": "GE", "dateDebut": "2013-04-08", "datePublication": null, "dateFin": "2017-06-20", "preseance": "20", "nominPrincipale": "1", "infosQualite": {"codeQualite": "Membre", "libQualite": "Membre", "libQualiteSex": "Membre"}, "organes": {"organeRef": "PO692283"}}, {"@xmlns:xsi": "http://www.w3.org/2001/XMLSchema-instance", "@xsi:type": "MandatSimple_Type", "uid": "PM751395", "acteurRef": "PA609726", "legislature": "15", "typeOrgane": "GE", "dateDebut": "2018-02-20", "datePublication": null, "dateFin": null, "preseance": "20", "nominPrincipale": "0", "infosQualite": {"codeQualite": "Membre", "libQualite": "Membre", "libQualiteSex": "Membre"}, "organes": {"organeRef": "PO746857"}}, {"@xmlns:xsi": "http://www.w3.org/2001/XMLSchema-instance", "@xsi:type": "MandatSimple_Type", "uid": "PM692907", "acteurRef": "PA609726", "legislature": "14", "typeOrgane": "GE", "dateDebut": "2013-03-25", "datePublication": null, "dateFin": "2017-06-20", "preseance": "20", "nominPrincipale": "1", "infosQualite": {"codeQualite": "Membre", "libQualite": "Membre", "libQualiteSex": "Membre"}, "organes": {"organeRef": "PO689030"}}, {"@xmlns:xsi": "http://www.w3.org/2001/XMLSchema-instance", "@xsi:type": "MandatSimple_Type", "uid": "PM690092", "acteurRef": "PA609726", "legislature": "14", "typeOrgane": "GE", "dateDebut": "2013-02-04", "datePublication": null, "dateFin": "2017-06-20", "preseance": "20", "nominPrincipale": "1", "infosQualite": {"codeQualite": "Membre", "libQualite": "Membre", "libQualiteSex": "Membre"}, "organes": {"organeRef": "PO686275"}}, {"@xmlns:xsi": "http://www.w3.org/2001/XMLSchema-instance", "@xsi:type": "MandatSimple_Type", "uid": "PM748887", "acteurRef": "PA609726", "legislature": "15", "typeOrgane": "GE", "dateDebut": "2018-02-01", "datePublication": null, "dateFin": null, "preseance": "1", "nominPrincipale": "1", "infosQualite": {"codeQualite": "Pr\u00e9sident", "libQualite": "Pr\u00e9sident", "libQualiteSex": "Pr\u00e9sident"}, "organes": {"organeRef": "PO746899"}}, {"@xmlns:xsi": "http://www.w3.org/2001/XMLSchema-instance", "@xsi:type": "MandatSimple_Type", "uid": "PM687757", "acteurRef": "PA609726", "legislature": "14", "typeOrgane": "GE", "dateDebut": "2013-01-15", "datePublication": null, "dateFin": "2017-06-20", "preseance": "20", "nominPrincipale": "1", "infosQualite": {"codeQualite": "Membre", "libQualite": "Membre", "libQualiteSex": "Membre"}, "organes": {"organeRef": "PO686415"}}, {"@xmlns:xsi": "http://www.w3.org/2001/XMLSchema-instance", "@xsi:type": "MandatSimple_Type", "uid": "PM752356", "acteurRef": "PA609726", "legislature": "15", "typeOrgane": "GE", "dateDebut": "2018-03-05", "datePublication": null, "dateFin": null, "preseance": "20", "nominPrincipale": "1", "infosQualite": {"codeQualite": "Membre", "libQualite": "Membre", "libQualiteSex": "Membre"}, "organes": {"organeRef": "PO747246"}}, {"@xmlns:xsi": "http://www.w3.org/2001/XMLSchema-instance", "@xsi:type": "MandatSimple_Type", "uid": "PM753839", "acteurRef": "PA609726", "legislature": "15", "typeOrgane": "GE", "dateDebut": "2018-03-19", "datePublication": null, "dateFin": null, "preseance": "20", "nominPrincipale": "1", "infosQualite": {"codeQualite": "Membre", "libQualite": "Membre", "libQualiteSex": "Membre"}, "organes": {"organeRef": "PO747150"}}, {"@xmlns:xsi": "http://www.w3.org/2001/XMLSchema-instance", "@xsi:type": "MandatSimple_Type", "uid": "PM687873", "acteurRef": "PA609726", "legislature": "14", "typeOrgane": "GE", "dateDebut": "2013-01-15", "datePublication": null, "dateFin": "2017-06-20", "preseance": "20", "nominPrincipale": "1", "infosQualite": {"codeQualite": "Membre", "libQualite": "Membre", "libQualiteSex": "Membre"}, "organes": {"organeRef": "PO686258"}}, {"@xmlns:xsi": "http://www.w3.org/2001/XMLSchema-instance", "@xsi:type": "MandatSimple_Type", "uid": "PM689198", "acteurRef": "PA609726", "legislature": "14", "typeOrgane": "GE", "dateDebut": "2013-02-01", "datePublication": null, "dateFin": "2017-06-20", "preseance": "20", "nominPrincipale": "1", "infosQualite": {"codeQualite": "Membre", "libQualite": "Membre", "libQualiteSex": "Membre"}, "organes": {"organeRef": "PO686510"}}, {"@xmlns:xsi": "http://www.w3.org/2001/XMLSchema-instance", "@xsi:type": "MandatSimple_Type", "uid": "PM688824", "acteurRef": "PA609726", "legislature": "14", "typeOrgane": "GE", "dateDebut": "2013-01-28", "datePublication": null, "dateFin": "2017-06-20", "preseance": "20", "nominPrincipale": "1", "infosQualite": {"codeQualite": "Membre", "libQualite": "Membre", "libQualiteSex": "Membre"}, "organes": {"organeRef": "PO686749"}}, {"@xmlns:xsi": "http://www.w3.org/2001/XMLSchema-instance", "@xsi:type": "MandatSimple_Type", "uid": "PM691338", "acteurRef": "PA609726", "legislature": "14", "typeOrgane": "GE", "dateDebut": "2013-02-12", "datePublication": null, "dateFin": "2017-06-20", "preseance": "20", "nominPrincipale": "1", "infosQualite": {"codeQualite": "Membre", "libQualite": "Membre", "libQualiteSex": "Membre"}, "organes": {"organeRef": "PO687120"}}, {"@xmlns:xsi": "http://www.w3.org/2001/XMLSchema-instance", "@xsi:type": "MandatSimple_Type", "uid": "PM695774", "acteurRef": "PA609726", "legislature": "14", "typeOrgane": "GE", "dateDebut": "2013-06-27", "datePublication": null, "dateFin": "2017-06-20", "preseance": "20", "nominPrincipale": "1", "infosQualite": {"codeQualite": "Membre", "libQualite": "Membre", "libQualiteSex": "Membre"}, "organes": {"organeRef": "PO688296"}}, {"@xmlns:xsi": "http://www.w3.org/2001/XMLSchema-instance", "@xsi:type": "MandatSimple_Type", "uid": "PM750224", "acteurRef": "PA609726", "legislature": "15", "typeOrgane": "GE", "dateDebut": "2018-02-12", "datePublication": null, "dateFin": null, "preseance": "20", "nominPrincipale": "1", "infosQualite": {"codeQualite": "Membre", "libQualite": "Membre", "libQualiteSex": "Membre"}, "organes": {"organeRef": "PO747266"}}, {"@xmlns:xsi": "http://www.w3.org/2001/XMLSchema-instance", "@xsi:type": "MandatSimple_Type", "uid": "PM687665", "acteurRef": "PA609726", "legislature": "14", "typeOrgane": "GE", "dateDebut": "2013-01-10", "datePublication": null, "dateFin": "2017-06-20", "preseance": "20", "nominPrincipale": "1", "infosQualite": {"codeQualite": "Membre", "libQualite": "Membre", "libQualiteSex": "Membre"}, "organes": {"organeRef": "PO686397"}}, {"@xmlns:xsi": "http://www.w3.org/2001/XMLSchema-instance", "@xsi:type": "MandatSimple_Type", "uid": "PM688690", "acteurRef": "PA609726", "legislature": "14", "typeOrgane": "GE", "dateDebut": "2013-01-25", "datePublication": null, "dateFin": "2017-06-20", "preseance": "20", "nominPrincipale": "1", "infosQualite": {"codeQualite": "Membre", "libQualite": "Membre", "libQualiteSex": "Membre"}, "organes": {"organeRef": "PO686501"}}, {"@xmlns:xsi": "http://www.w3.org/2001/XMLSchema-instance", "@xsi:type": "MandatSimple_Type", "uid": "PM688077", "acteurRef": "PA609726", "legislature": "14", "typeOrgane": "GE", "dateDebut": "2013-01-17", "datePublication": null, "dateFin": "2017-06-20", "preseance": "20", "nominPrincipale": "1", "infosQualite": {"codeQualite": "Membre", "libQualite": "Membre", "libQualiteSex": "Membre"}, "organes": {"organeRef": "PO686785"}}, {"@xmlns:xsi": "http://www.w3.org/2001/XMLSchema-instance", "@xsi:type": "MandatSimple_Type", "uid": "PM689171", "acteurRef": "PA609726", "legislature": "14", "typeOrgane": "GE", "dateDebut": "2013-01-14", "datePublication": null, "dateFin": "2017-06-20", "preseance": "20", "nominPrincipale": "1", "infosQualite": {"codeQualite": "Membre", "libQualite": "Membre", "libQualiteSex": "Membre"}, "organes": {"organeRef": "PO686617"}}, {"@xmlns:xsi": "http://www.w3.org/2001/XMLSchema-instance", "@xsi:type": "MandatSimple_Type", "uid": "PM689460", "acteurRef": "PA609726", "legislature": "14", "typeOrgane": "GE", "dateDebut": "2013-01-23", "datePublication": null, "dateFin": "2017-06-20", "preseance": "20", "nominPrincipale": "1", "infosQualite": {"codeQualite": "Membre", "libQualite": "Membre", "libQualiteSex": "Membre"}, "organes": {"organeRef": "PO687109"}}, {"@xmlns:xsi": "http://www.w3.org/2001/XMLSchema-instance", "@xsi:type": "MandatSimple_Type", "uid": "PM693064", "acteurRef": "PA609726", "legislature": "14", "typeOrgane": "GE", "dateDebut": "2013-02-01", "datePublication": null, "dateFin": "2017-06-20", "preseance": "20", "nominPrincipale": "1", "infosQualite": {"codeQualite": "Membre", "libQualite": "Membre", "libQualiteSex": "Membre"}, "organes": {"organeRef": "PO686354"}}, {"@xmlns:xsi": "http://www.w3.org/2001/XMLSchema-instance", "@xsi:type": "MandatSimple_Type", "uid": "PM686910", "acteurRef": "PA609726", "legislature": "14", "typeOrgane": "GA", "dateDebut": "2012-12-14", "datePublication": null, "dateFin": "2017-06-20", "preseance": "20", "nominPrincipale": "0", "infosQualite": {"codeQualite": "Membre", "libQualite": "Membre", "libQualiteSex": "Membre"}, "organes": {"organeRef": "PO675744"}}, {"@xmlns:xsi": "http://www.w3.org/2001/XMLSchema-instance", "@xsi:type": "MandatSimple_Type", "uid": "PM684490", "acteurRef": "PA609726", "legislature": "14", "typeOrgane": "GA", "dateDebut": "2012-11-14", "datePublication": null, "dateFin": "2017-06-20", "preseance": "20", "nominPrincipale": "1", "infosQualite": {"codeQualite": "Membre", "libQualite": "Membre", "libQualiteSex": "Membre"}, "organes": {"organeRef": "PO675761"}}, {"@xmlns:xsi": "http://www.w3.org/2001/XMLSchema-instance", "@xsi:type": "MandatSimple_Type", "uid": "PM738602", "acteurRef": "PA609726", "legislature": "15", "typeOrgane": "GA", "dateDebut": "2017-10-10", "datePublication": null, "dateFin": null, "preseance": "20", "nominPrincipale": "0", "infosQualite": {"codeQualite": "Membre", "libQualite": "Membre", "libQualiteSex": "Membre"}, "organes": {"organeRef": "PO733202"}}, {"@xmlns:xsi": "http://www.w3.org/2001/XMLSchema-instance", "@xsi:type": "MandatSimple_Type", "uid": "PM684488", "acteurRef": "PA609726", "legislature": "14", "typeOrgane": "GA", "dateDebut": "2012-11-14", "datePublication": null, "dateFin": "2017-06-20", "preseance": "20", "nominPrincipale": "1", "infosQualite": {"codeQualite": "Membre", "libQualite": "Membre", "libQualiteSex": "Membre"}, "organes": {"organeRef": "PO675847"}}, {"@xmlns:xsi": "http://www.w3.org/2001/XMLSchema-instance", "@xsi:type": "MandatSimple_Type", "uid": "PM684492", "acteurRef": "PA609726", "legislature": "14", "typeOrgane": "GA", "dateDebut": "2012-11-14", "datePublication": null, "dateFin": "2017-06-20", "preseance": "20", "nominPrincipale": "1", "infosQualite": {"codeQualite": "Membre", "libQualite": "Membre", "libQualiteSex": "Membre"}, "organes": {"organeRef": "PO675840"}}, {"@xmlns:xsi": "http://www.w3.org/2001/XMLSchema-instance", "@xsi:type": "MandatSimple_Type", "uid": "PM738604", "acteurRef": "PA609726", "legislature": "15", "typeOrgane": "GA", "dateDebut": "2017-10-10", "datePublication": null, "dateFin": null, "preseance": "20", "nominPrincipale": "1", "infosQualite": {"codeQualite": "Membre", "libQualite": "Membre", "libQualiteSex": "Membre"}, "organes": {"organeRef": "PO733382"}}, {"@xmlns:xsi": "http://www.w3.org/2001/XMLSchema-instance", "@xsi:type": "MandatSimple_Type", "uid": "PM685115", "acteurRef": "PA609726", "legislature": "14", "typeOrgane": "GA", "dateDebut": "2012-11-28", "datePublication": null, "dateFin": "2017-06-20", "preseance": "14", "nominPrincipale": "1", "infosQualite": {"codeQualite": "Secr\u00e9taire", "libQualite": "Secr\u00e9taire", "libQualiteSex": "Secr\u00e9taire"}, "organes": {"organeRef": "PO675837"}}, {"@xmlns:xsi": "http://www.w3.org/2001/XMLSchema-instance", "@xsi:type": "MandatSimple_Type", "uid": "PM740712", "acteurRef": "PA609726", "legislature": "15", "typeOrgane": "GA", "dateDebut": "2017-10-23", "datePublication": null, "dateFin": null, "preseance": "20", "nominPrincipale": "0", "infosQualite": {"codeQualite": "Membre", "libQualite": "Membre", "libQualiteSex": "Membre"}, "organes": {"organeRef": "PO733557"}}, {"@xmlns:xsi": "http://www.w3.org/2001/XMLSchema-instance", "@xsi:type": "MandatSimple_Type", "uid": "PM684494", "acteurRef": "PA609726", "legislature": "14", "typeOrgane": "GA", "dateDebut": "2012-11-14", "datePublication": null, "dateFin": "2017-06-20", "preseance": "20", "nominPrincipale": "1", "infosQualite": {"codeQualite": "Membre", "libQualite": "Membre", "libQualiteSex": "Membre"}, "organes": {"organeRef": "PO675830"}}, {"@xmlns:xsi": "http://www.w3.org/2001/XMLSchema-instance", "@xsi:type": "MandatSimple_Type", "uid": "PM684496", "acteurRef": "PA609726", "legislature": "14", "typeOrgane": "GA", "dateDebut": "2012-11-14", "datePublication": null, "dateFin": "2017-06-20", "preseance": "20", "nominPrincipale": "1", "infosQualite": {"codeQualite": "Membre", "libQualite": "Membre", "libQualiteSex": "Membre"}, "organes": {"organeRef": "PO675711"}}, {"@xmlns:xsi": "http://www.w3.org/2001/XMLSchema-instance", "@xsi:type": "MandatSimple_Type", "uid": "PM684498", "acteurRef": "PA609726", "legislature": "14", "typeOrgane": "GA", "dateDebut": "2012-11-14", "datePublication": null, "dateFin": "2017-06-20", "preseance": "20", "nominPrincipale": "1", "infosQualite": {"codeQualite": "Membre", "libQualite": "Membre", "libQualiteSex": "Membre"}, "organes": {"organeRef": "PO675849"}}, {"@xmlns:xsi": "http://www.w3.org/2001/XMLSchema-instance", "@xsi:type": "MandatSimple_Type", "uid": "PM689744", "acteurRef": "PA609726", "legislature": "14", "typeOrgane": "GA", "dateDebut": "2012-11-21", "datePublication": null, "dateFin": "2017-06-20", "preseance": "14", "nominPrincipale": "1", "infosQualite": {"codeQualite": "Secr\u00e9taire", "libQualite": "Secr\u00e9taire", "libQualiteSex": "Secr\u00e9taire"}, "organes": {"organeRef": "PO675772"}}, {"@xmlns:xsi": "http://www.w3.org/2001/XMLSchema-instance", "@xsi:type": "MandatSimple_Type", "uid": "PM679559", "acteurRef": "PA609726", "legislature": "14", "typeOrgane": "GA", "dateDebut": "2012-10-10", "datePublication": null, "dateFin": "2017-06-20", "preseance": "20", "nominPrincipale": "1", "infosQualite": {"codeQualite": "Membre", "libQualite": "Membre", "libQualiteSex": "Membre"}, "organes": {"organeRef": "PO675762"}}, {"@xmlns:xsi": "http://www.w3.org/2001/XMLSchema-instance", "@xsi:type": "MandatSimple_Type", "uid": "PM686911", "acteurRef": "PA609726", "legislature": "14", "typeOrgane": "GA", "dateDebut": "2012-12-14", "datePublication": null, "dateFin": "2017-06-20", "preseance": "1", "nominPrincipale": "1", "infosQualite": {"codeQualite": "Pr\u00e9sident", "libQualite": "Pr\u00e9sident", "libQualiteSex": "Pr\u00e9sident"}, "organes": {"organeRef": "PO675744"}}, {"@xmlns:xsi": "http://www.w3.org/2001/XMLSchema-instance", "@xsi:type": "MandatSimple_Type", "uid": "PM684491", "acteurRef": "PA609726", "legislature": "14", "typeOrgane": "GA", "dateDebut": "2012-11-14", "datePublication": null, "dateFin": "2017-06-20", "preseance": "20", "nominPrincipale": "1", "infosQualite": {"codeQualite": "Membre", "libQualite": "Membre", "libQualiteSex": "Membre"}, "organes": {"organeRef": "PO675811"}}, {"@xmlns:xsi": "http://www.w3.org/2001/XMLSchema-instance", "@xsi:type": "MandatSimple_Type", "uid": "PM738603", "acteurRef": "PA609726", "legislature": "15", "typeOrgane": "GA", "dateDebut": "2017-10-10", "datePublication": null, "dateFin": null, "preseance": "20", "nominPrincipale": "1", "infosQualite": {"codeQualite": "Membre", "libQualite": "Membre", "libQualiteSex": "Membre"}, "organes": {"organeRef": "PO733307"}}, {"@xmlns:xsi": "http://www.w3.org/2001/XMLSchema-instance", "@xsi:type": "MandatSimple_Type", "uid": "PM684489", "acteurRef": "PA609726", "legislature": "14", "typeOrgane": "GA", "dateDebut": "2012-11-14", "datePublication": null, "dateFin": "2017-06-20", "preseance": "20", "nominPrincipale": "1", "infosQualite": {"codeQualite": "Membre", "libQualite": "Membre", "libQualiteSex": "Membre"}, "organes": {"organeRef": "PO675837"}}, {"@xmlns:xsi": "http://www.w3.org/2001/XMLSchema-instance", "@xsi:type": "MandatSimple_Type", "uid": "PM684493", "acteurRef": "PA609726", "legislature": "14", "typeOrgane": "GA", "dateDebut": "2012-11-14", "datePublication": null, "dateFin": "2017-06-20", "preseance": "20", "nominPrincipale": "1", "infosQualite": {"codeQualite": "Membre", "libQualite": "Membre", "libQualiteSex": "Membre"}, "organes": {"organeRef": "PO675736"}}, {"@xmlns:xsi": "http://www.w3.org/2001/XMLSchema-instance", "@xsi:type": "MandatSimple_Type", "uid": "PM738605", "acteurRef": "PA609726", "legislature": "15", "typeOrgane": "GA", "dateDebut": "2017-10-10", "datePublication": null, "dateFin": null, "preseance": "20", "nominPrincipale": "1", "infosQualite": {"codeQualite": "Membre", "libQualite": "Membre", "libQualiteSex": "Membre"}, "organes": {"organeRef": "PO733567"}}, {"@xmlns:xsi": "http://www.w3.org/2001/XMLSchema-instance", "@xsi:type": "MandatSimple_Type", "uid": "PM684495", "acteurRef": "PA609726", "legislature": "14", "typeOrgane": "GA", "dateDebut": "2012-11-14", "datePublication": null, "dateFin": "2017-06-20", "preseance": "20", "nominPrincipale": "1", "infosQualite": {"codeQualite": "Membre", "libQualite": "Membre", "libQualiteSex": "Membre"}, "organes": {"organeRef": "PO675854"}}, {"@xmlns:xsi": "http://www.w3.org/2001/XMLSchema-instance", "@xsi:type": "MandatSimple_Type", "uid": "PM684497", "acteurRef": "PA609726", "legislature": "14", "typeOrgane": "GA", "dateDebut": "2012-11-14", "datePublication": null, "dateFin": "2017-06-20", "preseance": "20", "nominPrincipale": "1", "infosQualite": {"codeQualite": "Membre", "libQualite": "Membre", "libQualiteSex": "Membre"}, "organes": {"organeRef": "PO675791"}}, {"@xmlns:xsi": "http://www.w3.org/2001/XMLSchema-instance", "@xsi:type": "MandatSimple_Type", "uid": "PM684676", "acteurRef": "PA609726", "legislature": "14", "typeOrgane": "GA", "dateDebut": "2012-11-20", "datePublication": null, "dateFin": "2017-06-20", "preseance": "14", "nominPrincipale": "1", "infosQualite": {"codeQualite": "Secr\u00e9taire", "libQualite": "Secr\u00e9taire", "libQualiteSex": "Secr\u00e9taire"}, "organes": {"organeRef": "PO675736"}}, {"@xmlns:xsi": "http://www.w3.org/2001/XMLSchema-instance", "@xsi:type": "MandatSimple_Type", "uid": "PM684500", "acteurRef": "PA609726", "legislature": "14", "typeOrgane": "GA", "dateDebut": "2012-11-14", "datePublication": null, "dateFin": "2017-06-20", "preseance": "20", "nominPrincipale": "1", "infosQualite": {"codeQualite": "Membre", "libQualite": "Membre", "libQualiteSex": "Membre"}, "organes": {"organeRef": "PO675716"}}, {"@xmlns:xsi": "http://www.w3.org/2001/XMLSchema-instance", "@xsi:type": "MandatSimple_Type", "uid": "PM684499", "acteurRef": "PA609726", "legislature": "14", "typeOrgane": "GA", "dateDebut": "2012-11-14", "datePublication": null, "dateFin": "2017-06-20", "preseance": "20", "nominPrincipale": "1", "infosQualite": {"codeQualite": "Membre", "libQualite": "Membre", "libQualiteSex": "Membre"}, "organes": {"organeRef": "PO675781"}}, {"@xmlns:xsi": "http://www.w3.org/2001/XMLSchema-instance", "@xsi:type": "MandatSimple_Type", "uid": "PM679560", "acteurRef": "PA609726", "legislature": "14", "typeOrgane": "GA", "dateDebut": "2012-10-10", "datePublication": null, "dateFin": "2017-06-20", "preseance": "20", "nominPrincipale": "1", "infosQualite": {"codeQualite": "Membre", "libQualite": "Membre", "libQualiteSex": "Membre"}, "organes": {"organeRef": "PO675772"}}, {"@xmlns:xsi": "http://www.w3.org/2001/XMLSchema-instance", "@xsi:type": "MandatSimple_Type", "uid": "PM679558", "acteurRef": "PA609726", "legislature": "14", "typeOrgane": "GA", "dateDebut": "2012-10-10", "datePublication": null, "dateFin": "2017-06-20", "preseance": "20", "nominPrincipale": "1", "infosQualite": {"codeQualite": "Membre", "libQualite": "Membre", "libQualiteSex": "Membre"}, "organes": {"organeRef": "PO675751"}}, {"@xmlns:xsi": "http://www.w3.org/2001/XMLSchema-instance", "@xsi:type": "MandatSimple_Type", "uid": "PM690632", "acteurRef": "PA609726", "legislature": "14", "typeOrgane": "GE", "dateDebut": "2013-02-06", "datePublication": null, "dateFin": "2017-06-20", "preseance": "8", "nominPrincipale": "1", "infosQualite": {"codeQualite": "Vice-Pr\u00e9sident", "libQualite": "Vice-Pr\u00e9sident", "libQualiteSex": "Vice-Pr\u00e9sident"}, "organes": {"organeRef": "PO686275"}}, {"@xmlns:xsi": "http://www.w3.org/2001/XMLSchema-instance", "@xsi:type": "MandatSimple_Type", "uid": "PM752679", "acteurRef": "PA609726", "legislature": "15", "typeOrgane": "GE", "dateDebut": "2018-03-07", "datePublication": null, "dateFin": null, "preseance": "8", "nominPrincipale": "1", "infosQualite": {"codeQualite": "Vice-Pr\u00e9sident", "libQualite": "Vice-Pr\u00e9sident", "libQualiteSex": "Vice-Pr\u00e9sident"}, "organes": {"organeRef": "PO746857"}}, {"@xmlns:xsi": "http://www.w3.org/2001/XMLSchema-instance", "@xsi:type": "MandatSimple_Type", "uid": "PM694411", "acteurRef": "PA609726", "legislature": "14", "typeOrgane": "GE", "dateDebut": "2013-03-01", "datePublication": null, "dateFin": "2017-06-20", "preseance": "8", "nominPrincipale": "1", "infosQualite": {"codeQualite": "Vice-Pr\u00e9sident", "libQualite": "Vice-Pr\u00e9sident", "libQualiteSex": "Vice-Pr\u00e9sident"}, "organes": {"organeRef": "PO687403"}}, {"@xmlns:xsi": "http://www.w3.org/2001/XMLSchema-instance", "@xsi:type": "MandatSimple_Type", "uid": "PM687107", "acteurRef": "PA609726", "legislature": "14", "typeOrgane": "GE", "dateDebut": "2012-12-14", "datePublication": null, "dateFin": "2017-06-20", "preseance": "4", "nominPrincipale": "1", "infosQualite": {"codeQualite": "Co-Pr\u00e9sident", "libQualite": "Co-Pr\u00e9sident", "libQualiteSex": "Co-Pr\u00e9sident"}, "organes": {"organeRef": "PO687098"}}, {"@xmlns:xsi": "http://www.w3.org/2001/XMLSchema-instance", "@xsi:type": "MandatSimple_Type", "uid": "PM694295", "acteurRef": "PA609726", "legislature": "14", "typeOrgane": "GE", "dateDebut": "2013-04-16", "datePublication": null, "dateFin": "2017-06-20", "preseance": "8", "nominPrincipale": "1", "infosQualite": {"codeQualite": "Vice-Pr\u00e9sident", "libQualite": "Vice-Pr\u00e9sident", "libQualiteSex": "Vice-Pr\u00e9sident"}, "organes": {"organeRef": "PO689012"}}, {"@xmlns:xsi": "http://www.w3.org/2001/XMLSchema-instance", "@xsi:type": "MandatSimple_Type", "uid": "PM741794", "acteurRef": "PA609726", "legislature": "15", "typeOrgane": "GA", "dateDebut": "2017-10-26", "datePublication": null, "dateFin": null, "preseance": "8", "nominPrincipale": "1", "infosQualite": {"codeQualite": "Vice-Pr\u00e9sident", "libQualite": "Vice-Pr\u00e9sident", "libQualiteSex": "Vice-Pr\u00e9sident"}, "organes": {"organeRef": "PO733202"}}, {"@xmlns:xsi": "http://www.w3.org/2001/XMLSchema-instance", "@xsi:type": "MandatSimple_Type", "uid": "PM747417", "acteurRef": "PA609726", "legislature": "15", "typeOrgane": "GA", "dateDebut": "2017-12-20", "datePublication": null, "dateFin": null, "preseance": "8", "nominPrincipale": "1", "infosQualite": {"codeQualite": "Vice-Pr\u00e9sident", "libQualite": "Vice-Pr\u00e9sident", "libQualiteSex": "Vice-Pr\u00e9sident"}, "organes": {"organeRef": "PO733557"}}, {"@xmlns:xsi": "http://www.w3.org/2001/XMLSchema-instance", "@xsi:type": "MandatParlementaire_type", "uid": "PM645311", "acteurRef": "PA609726", "legislature": "14", "typeOrgane": "ASSEMBLEE", "dateDebut": "2012-06-20", "datePublication": null, "dateFin": "2017-06-20", "preseance": "50", "nominPrincipale": "1", "infosQualite": {"codeQualite": "membre", "libQualite": "membre", "libQualiteSex": "membre"}, "organes": {"organeRef": "PO644420"}, "suppleants": {"suppleant": {"dateDebut": "2012-06-20", "dateFin": "2017-06-20", "suppleantRef": "PA643110"}}, "chambre": null, "election": {"lieu": {"region": "Provence-Alpes-C\u00f4te d'Azur", "regionType": "M\u00e9tropolitain", "departement": "Vaucluse", "numDepartement": "84", "numCirco": "5"}, "causeMandat": "\u00e9lections g\u00e9n\u00e9rales", "refCirconscription": "PO645013"}, "mandature": {"datePriseFonction": "2012-06-20", "causeFin": "Fin de l\u00e9gislature", "premiereElection": "0", "placeHemicycle": "136", "mandatRemplaceRef": null}, "collaborateurs": null}, {"@xmlns:xsi": "http://www.w3.org/2001/XMLSchema-instance", "@xsi:type": "MandatParlementaire_type", "uid": "PM723426", "acteurRef": "PA609726", "legislature": "15", "typeOrgane": "ASSEMBLEE", "dateDebut": "2017-06-18", "datePublication": null, "dateFin": null, "preseance": "50", "nominPrincipale": "1", "infosQualite": {"codeQualite": "membre", "libQualite": "membre", "libQualiteSex": "membre"}, "organes": {"organeRef": "PO717460"}, "suppleants": {"suppleant": {"dateDebut": "2017-06-18", "dateFin": null, "suppleantRef": "PA721936"}}, "chambre": null, "election": {"lieu": {"region": "Provence-Alpes-C\u00f4te d'Azur", "regionType": "M\u00e9tropolitain", "departement": "Vaucluse", "numDepartement": "84", "numCirco": "5"}, "causeMandat": "\u00e9lections g\u00e9n\u00e9rales", "refCirconscription": "PO718594"}, "mandature": {"datePriseFonction": "2017-06-21", "causeFin": null, "premiereElection": "1", "placeHemicycle": "136", "mandatRemplaceRef": null}, "collaborateurs": {"collaborateur": [{"qualite": "M.", "prenom": "Bernard", "nom": "Hulin", "dateDebut": null, "dateFin": null}, {"qualite": "Mme", "prenom": "Delphine", "nom": "Cresp", "dateDebut": null, "dateFin": null}, {"qualite": "M.", "prenom": "Ga\u00ebtan", "nom": "Inard", "dateDebut": null, "dateFin": null}, {"qualite": "Mme", "prenom": "Colette", "nom": "Moni", "dateDebut": null, "dateFin": null}, {"qualite": "M.", "prenom": "Bastien", "nom": "Tissier", "dateDebut": null, "dateFin": null}]}}]}}}