{"acteur": {"@xmlns": "http://schemas.assemblee-nationale.fr/referentiel", "uid": {"@xmlns:xsi": "http://www.w3.org/2001/XMLSchema-instance", "@xsi:type": "IdActeur_type", "#text": "PA721166"}, "etatCivil": {"ident": {"civ": "Mme", "prenom": "Samantha", "nom": "Cazebonne", "alpha": "Cazebonne_samantha", "trigramme": {"@xmlns:xsi": "http://www.w3.org/2001/XMLSchema-instance", "@xsi:nil": "true"}}, "infoNaissance": {"dateNais": "1971-08-10", "villeNais": "La Rochelle", "depNais": "Charente-Maritime", "paysNais": "France"}, "dateDeces": {"@xmlns:xsi": "http://www.w3.org/2001/XMLSchema-instance", "@xsi:nil": "true"}}, "profession": {"libelleCourant": "Profession rattach\u00e9e \u00e0 l'enseignement", "socProcINSEE": {"catSocPro": "Cadres de la fonction publique, professions intellectuelles et  artistiques", "famSocPro": "Cadres et professions intellectuelles sup\u00e9rieures"}}, "uri_hatvp": {"@xmlns:xsi": "http://www.w3.org/2001/XMLSchema-instance", "@xsi:nil": "true"}, "adresses": {"adresse": [{"@xmlns:xsi": "http://www.w3.org/2001/XMLSchema-instance", "@xsi:type": "AdressePostale_Type", "uid": "AD721168", "type": "0", "typeLibelle": "Adresse officielle", "poids": "1", "adresseDeRattachement": null, "intitule": "Assembl\u00e9e nationale,", "numeroRue": "126", "nomRue": "Rue de l'Universit\u00e9,", "complementAdresse": null, "codePostal": "75355", "ville": "Paris 07 SP"}, {"@xmlns:xsi": "http://www.w3.org/2001/XMLSchema-instance", "@xsi:type": "AdresseMail_Type", "uid": "AD728221", "type": "15", "typeLibelle": "M\u00e8l", "poids": null, "adresseDeRattachement": null, "valElec": "samantha.cazebonne@assemblee-nationale.fr"}, {"@xmlns:xsi": "http://www.w3.org/2001/XMLSchema-instance", "@xsi:type": "AdresseTelephonique_Type", "uid": "AD757779", "type": "11", "typeLibelle": "T\u00e9l\u00e9phone", "poids": "1", "adresseDeRattachement": "AD721168", "valElec": "01.40.63.74.23"}, {"@xmlns:xsi": "http://www.w3.org/2001/XMLSchema-instance", "@xsi:type": "AdresseSiteWeb_Type", "uid": "AD785859", "type": "23", "typeLibelle": "Url s\u00e9nateur", "poids": null, "adresseDeRattachement": null, "valElec": "https://www.senat.fr/senateur/cazebonne_samantha19057m.html"}]}, "mandats": {"mandat": [{"@xmlns:xsi": "http://www.w3.org/2001/XMLSchema-instance", "@xsi:type": "MandatSimple_Type", "uid": "PM786475", "acteurRef": "PA721166", "legislature": null, "typeOrgane": "DELEGSENAT", "dateDebut": "2021-10-12", "datePublication": null, "dateFin": null, "preseance": "4", "nominPrincipale": "1", "infosQualite": {"codeQualite": "Membre", "libQualite": "Membre", "libQualiteSex": "Membre"}, "organes": {"organeRef": "PO310693"}}, {"@xmlns:xsi": "http://www.w3.org/2001/XMLSchema-instance", "@xsi:type": "MandatMission_Type", "uid": "PM757262", "acteurRef": "PA721166", "legislature": "15", "typeOrgane": "MISINFOPRE", "dateDebut": "2018-06-26", "datePublication": "2018-06-27", "dateFin": "2019-01-15", "preseance": "20", "nominPrincipale": "1", "infosQualite": {"codeQualite": "Membre", "libQualite": "Membre", "libQualiteSex": "Membre"}, "organes": {"organeRef": "PO757118"}, "libelle": null, "missionSuivanteRef": null, "missionPrecedenteRef": null}, {"@xmlns:xsi": "http://www.w3.org/2001/XMLSchema-instance", "@xsi:type": "MandatSimple_Type", "uid": "PM745037", "acteurRef": "PA721166", "legislature": null, "typeOrgane": "PARPOL", "dateDebut": "2017-12-01", "datePublication": null, "dateFin": "2018-11-30", "preseance": "5", "nominPrincipale": "1", "infosQualite": {"codeQualite": "Membre", "libQualite": "Membre", "libQualiteSex": "Membre"}, "organes": {"organeRef": "PO744854"}}, {"@xmlns:xsi": "http://www.w3.org/2001/XMLSchema-instance", "@xsi:type": "MandatSimple_Type", "uid": "PM761393", "acteurRef": "PA721166", "legislature": null, "typeOrgane": "PARPOL", "dateDebut": "2018-12-01", "datePublication": null, "dateFin": null, "preseance": "5", "nominPrincipale": "1", "infosQualite": {"codeQualite": "Membre", "libQualite": "Membre", "libQualiteSex": "Membre"}, "organes": {"organeRef": "PO761294"}}, {"@xmlns:xsi": "http://www.w3.org/2001/XMLSchema-instance", "@xsi:type": "MandatSimple_Type", "uid": "PM786132", "acteurRef": "PA721166", "legislature": null, "typeOrgane": "COMSENAT", "dateDebut": "2021-10-05", "datePublication": null, "dateFin": null, "preseance": "10", "nominPrincipale": "1", "infosQualite": {"codeQualite": "Membre", "libQualite": "Membre", "libQualiteSex": "Membre"}, "organes": {"organeRef": "PO211490"}}, {"@xmlns:xsi": "http://www.w3.org/2001/XMLSchema-instance", "@xsi:type": "MandatSimple_Type", "uid": "PM742130", "acteurRef": "PA721166", "legislature": "15", "typeOrgane": "API", "dateDebut": "2017-10-27", "datePublication": "2017-10-28", "dateFin": "2018-02-02", "preseance": "20", "nominPrincipale": "1", "infosQualite": {"codeQualite": "Membre", "libQualite": "Membre", "libQualiteSex": "Membre"}, "organes": {"organeRef": "PO201115"}}, {"@xmlns:xsi": "http://www.w3.org/2001/XMLSchema-instance", "@xsi:type": "MandatSimple_Type", "uid": "PM758941", "acteurRef": "PA721166", "legislature": "15", "typeOrgane": "API", "dateDebut": "2018-09-11", "datePublication": "2018-09-12", "dateFin": "2021-10-01", "preseance": "20", "nominPrincipale": "1", "infosQualite": {"codeQualite": "Membre", "libQualite": "Membre", "libQualiteSex": "Membre"}, "organes": {"organeRef": "PO201115"}}, {"@xmlns:xsi": "http://www.w3.org/2001/XMLSchema-instance", "@xsi:type": "MandatMission_Type", "uid": "PM766894", "acteurRef": "PA721166", "legislature": "15", "typeOrgane": "MISINFO", "dateDebut": "2019-07-23", "datePublication": null, "dateFin": "2021-10-01", "preseance": "10", "nominPrincipale": "0", "infosQualite": {"codeQualite": "Membre", "libQualite": "Membre", "libQualiteSex": "Membre"}, "organes": {"organeRef": "PO766891"}, "libelle": null, "missionSuivanteRef": null, "missionPrecedenteRef": null}, {"@xmlns:xsi": "http://www.w3.org/2001/XMLSchema-instance", "@xsi:type": "MandatSimple_Type", "uid": "PM786033", "acteurRef": "PA721166", "legislature": null, "typeOrgane": "GROUPESENAT", "dateDebut": "2021-10-01", "datePublication": null, "dateFin": null, "preseance": "4", "nominPrincipale": "1", "infosQualite": {"codeQualite": "Membre", "libQualite": "Membre", "libQualiteSex": "Membre du"}, "organes": {"organeRef": "PO732421"}}, {"@xmlns:xsi": "http://www.w3.org/2001/XMLSchema-instance", "@xsi:type": "MandatSimple_Type", "uid": "PM756025", "acteurRef": "PA721166", "legislature": "15", "typeOrgane": "GP", "dateDebut": "2018-05-09", "datePublication": "2018-05-10", "dateFin": "2021-10-01", "preseance": "20", "nominPrincipale": "1", "infosQualite": {"codeQualite": "Membre", "libQualite": "Membre du", "libQualiteSex": "Membre du"}, "organes": {"organeRef": "PO730964"}}, {"@xmlns:xsi": "http://www.w3.org/2001/XMLSchema-instance", "@xsi:type": "MandatSimple_Type", "uid": "PM731182", "acteurRef": "PA721166", "legislature": "15", "typeOrgane": "GP", "dateDebut": "2017-06-27", "datePublication": "2017-06-28", "dateFin": "2018-02-02", "preseance": "20", "nominPrincipale": "1", "infosQualite": {"codeQualite": "Membre", "libQualite": "Membre du", "libQualiteSex": "Membre du"}, "organes": {"organeRef": "PO730964"}}, {"@xmlns:xsi": "http://www.w3.org/2001/XMLSchema-instance", "@xsi:type": "MandatSimple_Type", "uid": "PM732099", "acteurRef": "PA721166", "legislature": "15", "typeOrgane": "COMPER", "dateDebut": "2017-06-29", "datePublication": "2017-06-29", "dateFin": "2018-02-02", "preseance": "32", "nominPrincipale": "1", "infosQualite": {"codeQualite": "Membre", "libQualite": "Membre", "libQualiteSex": "Membre"}, "organes": {"organeRef": "PO59047"}}, {"@xmlns:xsi": "http://www.w3.org/2001/XMLSchema-instance", "@xsi:type": "MandatSimple_Type", "uid": "PM756024", "acteurRef": "PA721166", "legislature": "15", "typeOrgane": "COMPER", "dateDebut": "2018-05-10", "datePublication": "2018-05-10", "dateFin": "2021-09-30", "preseance": "32", "nominPrincipale": "1", "infosQualite": {"codeQualite": "Membre", "libQualite": "Membre", "libQualiteSex": "Membre"}, "organes": {"organeRef": "PO59047"}}, {"@xmlns:xsi": "http://www.w3.org/2001/XMLSchema-instance", "@xsi:type": "MandatMission_Type", "uid": "PM766895", "acteurRef": "PA721166", "legislature": "15", "typeOrgane": "MISINFO", "dateDebut": "2019-07-23", "datePublication": null, "dateFin": "2021-10-01", "preseance": "5", "nominPrincipale": "1", "infosQualite": {"codeQualite": "Co-rapporteur", "libQualite": "Co-rapporteur", "libQualiteSex": "Co-rapporteure"}, "organes": {"organeRef": "PO766891"}, "libelle": null, "missionSuivanteRef": null, "missionPrecedenteRef": null}, {"@xmlns:xsi": "http://www.w3.org/2001/XMLSchema-instance", "@xsi:type": "MandatSimple_Type", "uid": "PM756895", "acteurRef": "PA721166", "legislature": "15", "typeOrgane": "ORGEXTPARL", "dateDebut": "2018-06-11", "datePublication": "2018-06-12", "dateFin": "2021-10-01", "preseance": "20", "nominPrincipale": "1", "infosQualite": {"codeQualite": "Titulaire", "libQualite": "Membre titulaire", "libQualiteSex": "Membre titulaire"}, "organes": {"organeRef": "PO732334"}}, {"@xmlns:xsi": "http://www.w3.org/2001/XMLSchema-instance", "@xsi:type": "MandatSimple_Type", "uid": "PM743013", "acteurRef": "PA721166", "legislature": "15", "typeOrgane": "ORGEXTPARL", "dateDebut": "2017-11-10", "datePublication": "2017-11-11", "dateFin": "2018-02-02", "preseance": "20", "nominPrincipale": "1", "infosQualite": {"codeQualite": "Titulaire", "libQualite": "Membre titulaire", "libQualiteSex": "Membre titulaire"}, "organes": {"organeRef": "PO679161"}}, {"@xmlns:xsi": "http://www.w3.org/2001/XMLSchema-instance", "@xsi:type": "MandatSimple_Type", "uid": "PM756929", "acteurRef": "PA721166", "legislature": "15", "typeOrgane": "ORGEXTPARL", "dateDebut": "2021-06-24", "datePublication": "2021-06-24", "dateFin": "2021-10-01", "preseance": "20", "nominPrincipale": "1", "infosQualite": {"codeQualite": "Titulaire", "libQualite": "Membre titulaire", "libQualiteSex": "Membre titulaire"}, "organes": {"organeRef": "PO60255"}}, {"@xmlns:xsi": "http://www.w3.org/2001/XMLSchema-instance", "@xsi:type": "MandatSimple_Type", "uid": "PM744645", "acteurRef": "PA721166", "legislature": "15", "typeOrgane": "ORGEXTPARL", "dateDebut": "2017-11-10", "datePublication": "2017-11-11", "dateFin": "2018-02-02", "preseance": "20", "nominPrincipale": "1", "infosQualite": {"codeQualite": "Titulaire", "libQualite": "Membre titulaire", "libQualiteSex": "Membre titulaire"}, "organes": {"organeRef": "PO60255"}}, {"@xmlns:xsi": "http://www.w3.org/2001/XMLSchema-instance", "@xsi:type": "MandatSimple_Type", "uid": "PM756896", "acteurRef": "PA721166", "legislature": "15", "typeOrgane": "ORGEXTPARL", "dateDebut": "2018-05-31", "datePublication": "2018-06-01", "dateFin": "2021-10-01", "preseance": "20", "nominPrincipale": "1", "infosQualite": {"codeQualite": "Titulaire", "libQualite": "Membre titulaire", "libQualiteSex": "Membre titulaire"}, "organes": {"organeRef": "PO679161"}}, {"@xmlns:xsi": "http://www.w3.org/2001/XMLSchema-instance", "@xsi:type": "MandatSimple_Type", "uid": "PM756375", "acteurRef": "PA721166", "legislature": "15", "typeOrgane": "GE", "dateDebut": "2018-05-25", "datePublication": null, "dateFin": "2021-10-01", "preseance": "20", "nominPrincipale": "1", "infosQualite": {"codeQualite": "Membre", "libQualite": "Membre", "libQualiteSex": "Membre"}, "organes": {"organeRef": "PO746735"}}, {"@xmlns:xsi": "http://www.w3.org/2001/XMLSchema-instance", "@xsi:type": "MandatSimple_Type", "uid": "PM724637", "acteurRef": "PA721166", "legislature": "15", "typeOrgane": "GP", "dateDebut": "2017-06-21", "datePublication": null, "dateFin": "2017-06-26", "preseance": "28", "nominPrincipale": "1", "infosQualite": {"codeQualite": "D\u00e9put\u00e9 non-inscrit", "libQualite": "D\u00e9put\u00e9 non-inscrit", "libQualiteSex": "D\u00e9put\u00e9e non-inscrite"}, "organes": {"organeRef": "PO723569"}}, {"@xmlns:xsi": "http://www.w3.org/2001/XMLSchema-instance", "@xsi:type": "MandatSimple_Type", "uid": "PM755858", "acteurRef": "PA721166", "legislature": "15", "typeOrgane": "GP", "dateDebut": "2018-04-23", "datePublication": null, "dateFin": "2018-05-08", "preseance": "28", "nominPrincipale": "1", "infosQualite": {"codeQualite": "D\u00e9put\u00e9 non-inscrit", "libQualite": "D\u00e9put\u00e9 non-inscrit", "libQualiteSex": "D\u00e9put\u00e9e non-inscrite"}, "organes": {"organeRef": "PO723569"}}, {"@xmlns:xsi": "http://www.w3.org/2001/XMLSchema-instance", "@xsi:type": "MandatSimple_Type", "uid": "PM756027", "acteurRef": "PA721166", "legislature": "15", "typeOrgane": "GA", "dateDebut": "2018-04-23", "datePublication": null, "dateFin": "2021-10-01", "preseance": "1", "nominPrincipale": "1", "infosQualite": {"codeQualite": "Pr\u00e9sident", "libQualite": "Pr\u00e9sident", "libQualiteSex": "Pr\u00e9sidente"}, "organes": {"organeRef": "PO732939"}}, {"@xmlns:xsi": "http://www.w3.org/2001/XMLSchema-instance", "@xsi:type": "MandatSimple_Type", "uid": "PM756029", "acteurRef": "PA721166", "legislature": "15", "typeOrgane": "GA", "dateDebut": "2018-04-23", "datePublication": null, "dateFin": "2021-10-01", "preseance": "20", "nominPrincipale": "1", "infosQualite": {"codeQualite": "Membre", "libQualite": "Membre", "libQualiteSex": "Membre"}, "organes": {"organeRef": "PO733527"}}, {"@xmlns:xsi": "http://www.w3.org/2001/XMLSchema-instance", "@xsi:type": "MandatSimple_Type", "uid": "PM735525", "acteurRef": "PA721166", "legislature": "15", "typeOrgane": "GA", "dateDebut": "2017-09-27", "datePublication": null, "dateFin": "2018-02-02", "preseance": "20", "nominPrincipale": "1", "infosQualite": {"codeQualite": "Membre", "libQualite": "Membre", "libQualiteSex": "Membre"}, "organes": {"organeRef": "PO733342"}}, {"@xmlns:xsi": "http://www.w3.org/2001/XMLSchema-instance", "@xsi:type": "MandatSimple_Type", "uid": "PM735527", "acteurRef": "PA721166", "legislature": "15", "typeOrgane": "GA", "dateDebut": "2017-09-27", "datePublication": null, "dateFin": "2018-02-02", "preseance": "20", "nominPrincipale": "1", "infosQualite": {"codeQualite": "Membre", "libQualite": "Membre", "libQualiteSex": "Membre"}, "organes": {"organeRef": "PO733627"}}, {"@xmlns:xsi": "http://www.w3.org/2001/XMLSchema-instance", "@xsi:type": "MandatSimple_Type", "uid": "PM735387", "acteurRef": "PA721166", "legislature": "15", "typeOrgane": "GA", "dateDebut": "2017-09-26", "datePublication": null, "dateFin": "2018-02-02", "preseance": "1", "nominPrincipale": "1", "infosQualite": {"codeQualite": "Pr\u00e9sident", "libQualite": "Pr\u00e9sident", "libQualiteSex": "Pr\u00e9sidente"}, "organes": {"organeRef": "PO732939"}}, {"@xmlns:xsi": "http://www.w3.org/2001/XMLSchema-instance", "@xsi:type": "MandatSimple_Type", "uid": "PM756026", "acteurRef": "PA721166", "legislature": "15", "typeOrgane": "GA", "dateDebut": "2018-04-23", "datePublication": null, "dateFin": "2021-10-01", "preseance": "20", "nominPrincipale": "0", "infosQualite": {"codeQualite": "Membre", "libQualite": "Membre", "libQualiteSex": "Membre"}, "organes": {"organeRef": "PO732939"}}, {"@xmlns:xsi": "http://www.w3.org/2001/XMLSchema-instance", "@xsi:type": "MandatSimple_Type", "uid": "PM756030", "acteurRef": "PA721166", "legislature": "15", "typeOrgane": "GA", "dateDebut": "2018-04-23", "datePublication": null, "dateFin": "2021-10-01", "preseance": "20", "nominPrincipale": "1", "infosQualite": {"codeQualite": "Membre", "libQualite": "Membre", "libQualiteSex": "Membre"}, "organes": {"organeRef": "PO733627"}}, {"@xmlns:xsi": "http://www.w3.org/2001/XMLSchema-instance", "@xsi:type": "MandatSimple_Type", "uid": "PM756028", "acteurRef": "PA721166", "legislature": "15", "typeOrgane": "GA", "dateDebut": "2018-04-23", "datePublication": null, "dateFin": "2021-10-01", "preseance": "20", "nominPrincipale": "1", "infosQualite": {"codeQualite": "Membre", "libQualite": "Membre", "libQualiteSex": "Membre"}, "organes": {"organeRef": "PO733437"}}, {"@xmlns:xsi": "http://www.w3.org/2001/XMLSchema-instance", "@xsi:type": "MandatSimple_Type", "uid": "PM735526", "acteurRef": "PA721166", "legislature": "15", "typeOrgane": "GA", "dateDebut": "2017-09-27", "datePublication": null, "dateFin": "2018-02-02", "preseance": "20", "nominPrincipale": "1", "infosQualite": {"codeQualite": "Membre", "libQualite": "Membre", "libQualiteSex": "Membre"}, "organes": {"organeRef": "PO733527"}}, {"@xmlns:xsi": "http://www.w3.org/2001/XMLSchema-instance", "@xsi:type": "MandatSimple_Type", "uid": "PM735386", "acteurRef": "PA721166", "legislature": "15", "typeOrgane": "GA", "dateDebut": "2017-09-26", "datePublication": null, "dateFin": "2018-02-02", "preseance": "20", "nominPrincipale": "0", "infosQualite": {"codeQualite": "Membre", "libQualite": "Membre", "libQualiteSex": "Membre"}, "organes": {"organeRef": "PO732939"}}, {"@xmlns:xsi": "http://www.w3.org/2001/XMLSchema-instance", "@xsi:type": "MandatParlementaire_type", "uid": "PM785865", "acteurRef": "PA721166", "legislature": null, "typeOrgane": "SENAT", "dateDebut": "2021-10-01", "datePublication": null, "dateFin": null, "preseance": "20", "nominPrincipale": "1", "infosQualite": {"codeQualite": "S\u00e9nateur", "libQualite": "SENATEUR", "libQualiteSex": "S\u00e9nateur 5\u00e8me R\u00e9publique"}, "organes": {"organeRef": "PO78718"}, "suppleants": null, "chambre": null, "election": {"lieu": {"region": null, "regionType": null, "departement": null, "numDepartement": "997", "numCirco": null}, "causeMandat": null}, "mandature": {"datePriseFonction": null, "causeFin": null, "premiereElection": "0", "placeHemicycle": null, "mandatRemplaceRef": null}, "collaborateurs": null}, {"@xmlns:xsi": "http://www.w3.org/2001/XMLSchema-instance", "@xsi:type": "MandatSimple_Type", "uid": "PM758763", "acteurRef": "PA721166", "legislature": "15", "typeOrgane": "GE", "dateDebut": "2018-08-30", "datePublication": null, "dateFin": "2021-10-01", "preseance": "8", "nominPrincipale": "1", "infosQualite": {"codeQualite": "Vice-Pr\u00e9sident", "libQualite": "Vice-Pr\u00e9sident", "libQualiteSex": "Vice-Pr\u00e9sidente"}, "organes": {"organeRef": "PO746735"}}, {"@xmlns:xsi": "http://www.w3.org/2001/XMLSchema-instance", "@xsi:type": "MandatSimple_Type", "uid": "PM746362", "acteurRef": "PA721166", "legislature": "15", "typeOrgane": "GA", "dateDebut": "2017-11-15", "datePublication": null, "dateFin": "2018-02-02", "preseance": "8", "nominPrincipale": "1", "infosQualite": {"codeQualite": "Vice-Pr\u00e9sident", "libQualite": "Vice-Pr\u00e9sident", "libQualiteSex": "Vice-Pr\u00e9sidente"}, "organes": {"organeRef": "PO733527"}}, {"@xmlns:xsi": "http://www.w3.org/2001/XMLSchema-instance", "@xsi:type": "MandatMission_Type", "uid": "PM760061", "acteurRef": "PA721166", "legislature": "15", "typeOrgane": "MINISTERE", "dateDebut": "2018-10-17", "datePublication": null, "dateFin": "2019-01-25", "preseance": "1", "nominPrincipale": "1", "infosQualite": {"codeQualite": "en mission", "libQualite": "en mission", "libQualiteSex": "en mission"}, "organes": {"organeRef": ["PO729976", "PO759773"]}, "libelle": "Mission temporaire ayant pour objet la r\u00e9alisation de l\u2019objectif de doublement du nombre d\u2019\u00e9l\u00e8ves scolaris\u00e9s dans le r\u00e9seau d\u2019enseignement fran\u00e7ais \u00e0 l\u2019\u00e9tranger \u00e0 l\u2019horizon 2030.", "missionSuivanteRef": null, "missionPrecedenteRef": "PM758420"}, {"@xmlns:xsi": "http://www.w3.org/2001/XMLSchema-instance", "@xsi:type": "MandatMission_Type", "uid": "PM758420", "acteurRef": "PA721166", "legislature": "15", "typeOrgane": "MINISTERE", "dateDebut": "2018-07-26", "datePublication": "2018-07-27", "dateFin": "2018-10-16", "preseance": "1", "nominPrincipale": "1", "infosQualite": {"codeQualite": "en mission", "libQualite": "en mission", "libQualiteSex": "en mission"}, "organes": {"organeRef": ["PO729976", "PO729999"]}, "libelle": "Mission temporaire ayant pour objet la r\u00e9alisation de l\u2019objectif de doublement du nombre d\u2019\u00e9l\u00e8ves scolaris\u00e9s dans le r\u00e9seau d\u2019enseignement fran\u00e7ais \u00e0 l\u2019\u00e9tranger \u00e0 l\u2019horizon 2030.", "missionSuivanteRef": "PM760061", "missionPrecedenteRef": null}, {"@xmlns:xsi": "http://www.w3.org/2001/XMLSchema-instance", "@xsi:type": "MandatParlementaire_type", "uid": "PM755857", "acteurRef": "PA721166", "legislature": "15", "typeOrgane": "ASSEMBLEE", "dateDebut": "2018-04-22", "datePublication": null, "dateFin": "2021-10-01", "preseance": "50", "nominPrincipale": "1", "infosQualite": {"codeQualite": "membre", "libQualite": "membre", "libQualiteSex": "membre"}, "organes": {"organeRef": "PO717460"}, "suppleants": {"suppleant": {"dateDebut": "2018-04-22", "dateFin": "2021-10-01", "suppleantRef": "PA721170"}}, "chambre": null, "election": {"lieu": {"region": "Fran\u00e7ais \u00e9tablis hors de France", "regionType": "Fran\u00e7ais \u00e9tablis hors de France", "departement": "Fran\u00e7ais \u00e9tablis hors de France", "numDepartement": "099", "numCirco": "5"}, "causeMandat": "\u00e9lection partielle, suite \u00e0 l'annulation de l'\u00e9lection d'un d\u00e9put\u00e9", "refCirconscription": "PO718604"}, "mandature": {"datePriseFonction": "2018-04-23", "causeFin": "\u00c9lection au S\u00e9nat", "premiereElection": "1", "placeHemicycle": null, "mandatRemplaceRef": null}, "collaborateurs": null}, {"@xmlns:xsi": "http://www.w3.org/2001/XMLSchema-instance", "@xsi:type": "MandatParlementaire_type", "uid": "PM723192", "acteurRef": "PA721166", "legislature": "15", "typeOrgane": "ASSEMBLEE", "dateDebut": "2017-06-18", "datePublication": null, "dateFin": "2018-02-02", "preseance": "50", "nominPrincipale": "1", "infosQualite": {"codeQualite": "membre", "libQualite": "membre", "libQualiteSex": "membre"}, "organes": {"organeRef": "PO717460"}, "suppleants": {"suppleant": {"dateDebut": "2017-06-18", "dateFin": "2018-02-02", "suppleantRef": "PA721170"}}, "chambre": null, "election": {"lieu": {"region": "Fran\u00e7ais \u00e9tablis hors de France", "regionType": "Fran\u00e7ais \u00e9tablis hors de France", "departement": "Fran\u00e7ais \u00e9tablis hors de France", "numDepartement": "099", "numCirco": "5"}, "causeMandat": "\u00e9lections g\u00e9n\u00e9rales", "refCirconscription": "PO718604"}, "mandature": {"datePriseFonction": "2017-06-21", "causeFin": "Annulation de l'\u00e9lection sur d\u00e9cision du Conseil constitutionnel", "premiereElection": "0", "placeHemicycle": null, "mandatRemplaceRef": null}, "collaborateurs": null}]}}}